libcoveweb2/__init__.py
libcoveweb2/admin.py
libcoveweb2/apps.py
libcoveweb2/background_worker.py
libcoveweb2/celery.py
libcoveweb2/context_processors.py
libcoveweb2/forms.py
libcoveweb2/middleware.py
libcoveweb2/models.py
libcoveweb2/settings.py
libcoveweb2/urls.py
libcoveweb2/utils.py
libcoveweb2/views.py
libcoveweb2/management/__init__.py
libcoveweb2/management/commands/__init__.py
libcoveweb2/management/commands/expire_files.py
libcoveweb2/management/commands/reprocess_everything.py
libcoveweb2/migrations/0001_initial.py
libcoveweb2/migrations/0002_supplieddatafile_meta.py
libcoveweb2/migrations/0003_supplieddata_expired.py
libcoveweb2/migrations/0004_supplieddatafile_source_method.py
libcoveweb2/migrations/0005_url_uploads.py
libcoveweb2/migrations/0006_supplieddata_processed.py
libcoveweb2/migrations/0007_supplieddata_error.py
libcoveweb2/migrations/0008_auto_20230414_0851.py
libcoveweb2/migrations/__init__.py
libcoveweb2/process/__init__.py
libcoveweb2/process/base.py
libcoveweb2/process/utils.py
libcoveweb2/process/common_tasks/__init__.py
libcoveweb2/process/common_tasks/download_data_task.py
libcoveweb2/process/common_tasks/task_with_state.py
libcoveweb2/static/dataexplore/css/style.css
libcoveweb2/static/dataexplore/fonts/bootstrap/glyphicons-halflings-regular.eot
libcoveweb2/static/dataexplore/fonts/bootstrap/glyphicons-halflings-regular.svg
libcoveweb2/static/dataexplore/fonts/bootstrap/glyphicons-halflings-regular.ttf
libcoveweb2/static/dataexplore/fonts/bootstrap/glyphicons-halflings-regular.woff
libcoveweb2/static/dataexplore/fonts/bootstrap/glyphicons-halflings-regular.woff2
libcoveweb2/static/dataexplore/fonts/tick/tick.css
libcoveweb2/static/dataexplore/fonts/tick/tick.eot
libcoveweb2/static/dataexplore/fonts/tick/tick.svg
libcoveweb2/static/dataexplore/fonts/tick/tick.ttf
libcoveweb2/static/dataexplore/fonts/tick/tick.woff
libcoveweb2/static/dataexplore/fonts/tick/tick.woff2
libcoveweb2/templates/libcoveweb2/500.html
libcoveweb2-0.4.0.dist-info/LICENSE.rst
libcoveweb2-0.4.0.dist-info/METADATA
libcoveweb2-0.4.0.dist-info/WHEEL
libcoveweb2-0.4.0.dist-info/top_level.txt
libcoveweb2-0.4.0.dist-info/RECORD
